OpenAIManager/AssistantManager.py
OpenAIManager/Helpers.py
OpenAIManager/OpenAIManager.py
OpenAIManager/ThreadsManager.py
OpenAIManager/__init__.py
openai_manager/__init__.py
openai_manager/assistant_manager.py
openai_manager/helpers.py
openai_manager/openai_manager.py
openai_manager/threads_manager.py
openai_api_manager-0.0.6.dist-info/LICENSE.txt
openai_api_manager-0.0.6.dist-info/METADATA
openai_api_manager-0.0.6.dist-info/WHEEL
openai_api_manager-0.0.6.dist-info/top_level.txt
openai_api_manager-0.0.6.dist-info/RECORD
